README.rst
setup.py
hcpup/__init__.py
hcpup/__main__.py
hcpup/conf.py
hcpup/init.py
hcpup/log.py
hcpup/notify.py
hcpup/queue.py
hcpup/service.py
hcpup/up.py
hcpupd.egg-info/PKG-INFO
hcpupd.egg-info/SOURCES.txt
hcpupd.egg-info/dependency_links.txt
hcpupd.egg-info/entry_points.txt
hcpupd.egg-info/requires.txt
hcpupd.egg-info/top_level.txt
version/__init__.py