Metadata-Version: 1.1
Name: hcpupd
Version: 0.2.5
Summary: hcpupd - HCP upload daemon
Home-page: https://hcpupd.readthedocs.io
Author: Thorsten Simons
Author-email: sw@snomis.de
License: MIT
Keywords: HCP Hitachi Content Platform upload daemon
Platform: UNKNOWN
Classifier: Development Status :: 5 - Production/Stable
Classifier: Intended Audience :: System Administrators
Classifier: Topic :: System :: Archiving
Classifier: License :: OSI Approved :: MIT License
Classifier: Programming Language :: Python :: 3
Classifier: Operating System :: POSIX :: Linux
Classifier: Natural Language :: English
